README.rst
peewee_encrypted_field.py
setup.py
peewee_encrypted_field.egg-info/PKG-INFO
peewee_encrypted_field.egg-info/SOURCES.txt
peewee_encrypted_field.egg-info/dependency_links.txt
peewee_encrypted_field.egg-info/requires.txt
peewee_encrypted_field.egg-info/top_level.txt