Metadata-Version: 1.1
Name: peewee-encrypted-field
Version: 0.0.2
Summary: Field with encryption/decryption on save/read for use in Peewee ORM models
Home-page: https://github.com/brake/peewee_encrypted_field
Author: Constantin Roganov
Author-email: rccbox@gmail.com
License: UNKNOWN
Download-URL: https://github.com/brake/peewee_mssql/archive/0.0.2.zip
Keywords: database,ORM,peewee,encryption,fernet,ciphering
Platform: UNKNOWN
Classifier: Development Status :: 4 - Beta
Classifier: Programming Language :: Python
Classifier: Programming Language :: Python :: 2.7
Classifier: License :: OSI Approved :: MIT License
Classifier: Intended Audience :: Developers
Classifier: Topic :: Database
Classifier: Topic :: Security
Classifier: Topic :: Security :: Cryptography
